hackassembler/__init__.py
hackassembler/assembler.py
hackassembler/code.py
hackassembler/commands.py
hackassembler/parser.py
hackassembler_cli-0.1.0.dist-info/METADATA
hackassembler_cli-0.1.0.dist-info/WHEEL
hackassembler_cli-0.1.0.dist-info/entry_points.txt
hackassembler_cli-0.1.0.dist-info/top_level.txt
hackassembler_cli-0.1.0.dist-info/RECORD
